async_http/__init__.py
async_http/app.py
async_http/cookie.py
async_http/error_handler.py
async_http/exceptions.py
async_http/protocol.py
async_http/request.py
async_http/response.py
async_http/router.py
async_http/server.py
async_http_minimal-0.0.4.dist-info/AUTHORS
async_http_minimal-0.0.4.dist-info/LICENSE
async_http_minimal-0.0.4.dist-info/METADATA
async_http_minimal-0.0.4.dist-info/WHEEL
async_http_minimal-0.0.4.dist-info/pbr.json
async_http_minimal-0.0.4.dist-info/top_level.txt
async_http_minimal-0.0.4.dist-info/RECORD
